identitwin/__init__.py
identitwin/calibration.py
identitwin/configurator.py
identitwin/event_monitoring.py
identitwin/performance_monitor.py
identitwin/processing_analysis.py
identitwin/processing_data.py
identitwin/report_generator.py
identitwin/simulator.py
identitwin/state.py
identitwin/system_monitoring.py
identitwin/visualization.py
identitwin-0.1.0.dist-info/LICENSE
identitwin-0.1.0.dist-info/METADATA
identitwin-0.1.0.dist-info/WHEEL
identitwin-0.1.0.dist-info/RECORD
