Metadata-Version: 2.3
Name: identitwin
Version: 0.1.0
Summary: IdentiTwin a system for structural monitoring.
Author: Ing. Angel Navarro-Mora M.Sc
Author-email: ahnavarro@itcr.ac.cr
Requires-Python: >=3.8,<4.0
Classifier: Programming Language :: Python :: 3
Classifier: Programming Language :: Python :: 3.8
Classifier: Programming Language :: Python :: 3.9
Classifier: Programming Language :: Python :: 3.10
Classifier: Programming Language :: Python :: 3.11
Classifier: Programming Language :: Python :: 3.12
Classifier: Programming Language :: Python :: 3.13
Provides-Extra: all
Provides-Extra: hardware
Provides-Extra: performance
Requires-Dist: adafruit-blinka ; extra == "hardware" or extra == "all"
Requires-Dist: adafruit-circuitpython-ads1x15 ; extra == "hardware" or extra == "all"
Requires-Dist: colorama
Requires-Dist: gpiozero ; extra == "hardware" or extra == "all"
Requires-Dist: matplotlib
Requires-Dist: mpu6050-raspberrypi ; extra == "hardware" or extra == "all"
Requires-Dist: numpy
Requires-Dist: psutil ; extra == "performance" or extra == "all"
Requires-Dist: sphinx
Requires-Dist: sphinx-autodoc-typehints
Requires-Dist: sphinx-rtd-theme
